{
  "vocabulary": {
    "words": [
      {
        "id": 207,
        "word": "air",
        "phonetic": "",
        "pos": "n.(U)",
        "meaning": "空气；大气",
        "example": "",
        "irregular_forms": {},
        "category": "其他",
        "difficulty": 2,
        "enabled": true,
        "created_at": "2026-01-14 03:03:21",
        "updated_at": "2026-01-14 03:03:21",
        "_source": "database",
        "_matchScore": 1
      },
      {
        "id": 344,
        "word": "become",
        "phonetic": "",
        "pos": "v.",
        "meaning": "变得；成为",
        "example": "",
        "irregular_forms": {},
        "category": "动词短语",
        "difficulty": 2,
        "enabled": true,
        "created_at": "2026-01-14 03:03:21",
        "updated_at": "2026-01-14 03:03:21",
        "_source": "database",
        "_matchScore": 1
      },
      {
        "id": 563,
        "word": "clean",
        "phonetic": "",
        "pos": "adj.",
        "meaning": "干净的；清洁的 v.打扫；弄干净；擦干净",
        "example": "",
        "irregular_forms": {},
        "category": "运动",
        "difficulty": 2,
        "enabled": true,
        "created_at": "2026-01-14 03:03:22",
        "updated_at": "2026-01-14 03:03:22",
        "_source": "database",
        "_matchScore": 1
      },
      {
        "id": 927,
        "word": "environment",
        "phonetic": "",
        "pos": "n.",
        "meaning": "环境",
        "example": "",
        "irregular_forms": {},
        "category": "其他",
        "difficulty": 2,
        "enabled": true,
        "created_at": "2026-01-14 03:03:22",
        "updated_at": "2026-01-14 03:03:22",
        "_source": "database",
        "_matchScore": 1
      },
      {
        "id": 1368,
        "word": "importance",
        "phonetic": "",
        "pos": "n.",
        "meaning": "重要性",
        "example": "",
        "irregular_forms": {},
        "category": "其他",
        "difficulty": 2,
        "enabled": true,
        "created_at": "2026-01-14 03:03:23",
        "updated_at": "2026-01-14 03:03:23",
        "_source": "database",
        "_matchScore": 1
      },
      {
        "id": 1369,
        "word": "important",
        "phonetic": "",
        "pos": "adj.",
        "meaning": "重要的",
        "example": "",
        "irregular_forms": {},
        "category": "其他",
        "difficulty": 2,
        "enabled": true,
        "created_at": "2026-01-14 03:03:23",
        "updated_at": "2026-01-14 03:03:23",
        "_source": "database",
        "_matchScore": 1
      },
      {
        "id": 1875,
        "word": "plant",
        "phonetic": "",
        "pos": "n.(C)",
        "meaning": "植物 vt.种植；播种",
        "example": "",
        "irregular_forms": {},
        "category": "其他",
        "difficulty": 2,
        "enabled": true,
        "created_at": "2026-01-14 03:03:24",
        "updated_at": "2026-01-14 03:03:24",
        "_source": "database",
        "_matchScore": 1
      },
      {
        "id": 1986,
        "word": "protect",
        "phonetic": "",
        "pos": "",
        "meaning": "vt.保护",
        "example": "",
        "irregular_forms": {},
        "category": "其他",
        "difficulty": 2,
        "enabled": true,
        "created_at": "2026-01-14 03:03:24",
        "updated_at": "2026-01-14 03:03:24",
        "_source": "database",
        "_matchScore": 1
      },
      {
        "id": 2528,
        "word": "title",
        "phonetic": "",
        "pos": "n.(C)",
        "meaning": "标题",
        "example": "",
        "irregular_forms": {},
        "category": "其他",
        "difficulty": 2,
        "enabled": true,
        "created_at": "2026-01-14 03:03:26",
        "updated_at": "2026-01-14 03:03:26",
        "_source": "database",
        "_matchScore": 1
      },
      {
        "id": 225,
        "word": "amaze",
        "phonetic": "",
        "pos": "v.",
        "meaning": "使惊奇",
        "example": "",
        "irregular_forms": {},
        "category": "其他",
        "difficulty": 2,
        "enabled": true,
        "created_at": "2026-01-14 03:03:21",
        "updated_at": "2026-01-14 03:03:21",
        "_source": "database",
        "_matchScore": 1
      },
      {
        "id": 624,
        "word": "conduct",
        "phonetic": "",
        "pos": "v.",
        "meaning": "传导；指挥；执行",
        "example": "",
        "irregular_forms": {},
        "category": "其他",
        "difficulty": 2,
        "enabled": true,
        "created_at": "2026-01-14 03:03:22",
        "updated_at": "2026-01-14 03:03:22",
        "_source": "database",
        "_matchScore": 1
      },
      {
        "id": 651,
        "word": "control",
        "phonetic": "",
        "pos": "v.",
        "meaning": "& n.(U)控制",
        "example": "",
        "irregular_forms": {},
        "category": "其他",
        "difficulty": 2,
        "enabled": true,
        "created_at": "2026-01-14 03:03:22",
        "updated_at": "2026-01-14 03:03:22",
        "_source": "database",
        "_matchScore": 1
      },
      {
        "id": 695,
        "word": "crowd",
        "phonetic": "",
        "pos": "n.(C)",
        "meaning": "人群 v.(使)挤满",
        "example": "",
        "irregular_forms": {},
        "category": "其他",
        "difficulty": 2,
        "enabled": true,
        "created_at": "2026-01-14 03:03:22",
        "updated_at": "2026-01-14 03:03:22",
        "_source": "database",
        "_matchScore": 1
      },
      {
        "id": 2791,
        "word": "essential",
        "phonetic": "/ɪˈsenʃl/",
        "pos": "adj.",
        "meaning": "极其重要的，必不可少的",
        "example": "Proper preparation is essential for a successful experiment.",
        "irregular_forms": {},
        "category": "其他",
        "difficulty": 2,
        "enabled": true,
        "created_at": "2026-01-16 00:57:19",
        "updated_at": "2026-01-16 00:57:19",
        "_source": "database",
        "_matchScore": 1
      },
      {
        "id": 982,
        "word": "experiment",
        "phonetic": "",
        "pos": "n.",
        "meaning": "实验",
        "example": "",
        "irregular_forms": {},
        "category": "其他",
        "difficulty": 2,
        "enabled": true,
        "created_at": "2026-01-14 03:03:22",
        "updated_at": "2026-01-14 03:03:22",
        "_source": "database",
        "_matchScore": 1
      },
      {
        "id": 980,
        "word": "experience",
        "phonetic": "",
        "pos": "n.",
        "meaning": "经验；经历",
        "example": "",
        "irregular_forms": {},
        "category": "其他",
        "difficulty": 2,
        "enabled": true,
        "created_at": "2026-01-14 03:03:22",
        "updated_at": "2026-01-14 03:03:22",
        "_source": "database",
        "_matchScore": 1
      },
      {
        "id": 1698,
        "word": "nervous",
        "phonetic": "",
        "pos": "adj.",
        "meaning": "紧张的",
        "example": "",
        "irregular_forms": {},
        "category": "情感",
        "difficulty": 2,
        "enabled": true,
        "created_at": "2026-01-14 03:03:24",
        "updated_at": "2026-01-14 03:03:24",
        "_source": "database",
        "_matchScore": 1
      },
      {
        "id": 1943,
        "word": "preparation",
        "phonetic": "",
        "pos": "n.",
        "meaning": "(U/C)准备；准备工作",
        "example": "",
        "irregular_forms": {},
        "category": "其他",
        "difficulty": 2,
        "enabled": true,
        "created_at": "2026-01-14 03:03:24",
        "updated_at": "2026-01-14 03:03:24",
        "_source": "database",
        "_matchScore": 1
      },
      {
        "id": 1984,
        "word": "proper",
        "phonetic": "",
        "pos": "adj.",
        "meaning": "合适的",
        "example": "",
        "irregular_forms": {},
        "category": "其他",
        "difficulty": 2,
        "enabled": true,
        "created_at": "2026-01-14 03:03:24",
        "updated_at": "2026-01-14 03:03:24",
        "_source": "database",
        "_matchScore": 1
      },
      {
        "id": 2347,
        "word": "speech",
        "phonetic": "",
        "pos": "n.",
        "meaning": "(U/C)说话；演讲",
        "example": "",
        "irregular_forms": {},
        "category": "其他",
        "difficulty": 2,
        "enabled": true,
        "created_at": "2026-01-14 03:03:25",
        "updated_at": "2026-01-14 03:03:25",
        "_source": "database",
        "_matchScore": 1
      },
      {
        "id": 2445,
        "word": "system",
        "phonetic": "",
        "pos": "n.(C)",
        "meaning": "系统；体系",
        "example": "",
        "irregular_forms": {},
        "category": "其他",
        "difficulty": 2,
        "enabled": true,
        "created_at": "2026-01-14 03:03:25",
        "updated_at": "2026-01-14 03:03:25",
        "_source": "database",
        "_matchScore": 1
      },
      {
        "id": 1098,
        "word": "foreign",
        "phonetic": "",
        "pos": "adj.",
        "meaning": "外国的",
        "example": "",
        "irregular_forms": {},
        "category": "其他",
        "difficulty": 2,
        "enabled": true,
        "created_at": "2026-01-14 03:03:23",
        "updated_at": "2026-01-14 03:03:23",
        "_source": "database",
        "_matchScore": 1
      },
      {
        "id": 2792,
        "word": "fluently",
        "phonetic": "/ˈfluːəntli/",
        "pos": "adv.",
        "meaning": "流利地",
        "example": "She can speak English fluently.",
        "irregular_forms": {},
        "category": "其他",
        "difficulty": 2,
        "enabled": true,
        "created_at": "2026-01-16 00:57:37",
        "updated_at": "2026-01-16 00:57:37",
        "_source": "database",
        "_matchScore": 1
      },
      {
        "id": 1491,
        "word": "language",
        "phonetic": "",
        "pos": "n.",
        "meaning": "语言",
        "example": "",
        "irregular_forms": {},
        "category": "其他",
        "difficulty": 2,
        "enabled": true,
        "created_at": "2026-01-14 03:03:23",
        "updated_at": "2026-01-14 03:03:23",
        "_source": "database",
        "_matchScore": 1
      },
      {
        "id": 1598,
        "word": "married",
        "phonetic": "",
        "pos": "adj.",
        "meaning": "已婚的",
        "example": "",
        "irregular_forms": {},
        "category": "其他",
        "difficulty": 2,
        "enabled": true,
        "created_at": "2026-01-14 03:03:24",
        "updated_at": "2026-01-14 03:03:24",
        "_source": "database",
        "_matchScore": 1
      },
      {
        "id": 2014,
        "word": "quiet",
        "phonetic": "",
        "pos": "adj.",
        "meaning": "安静的",
        "example": "",
        "irregular_forms": {},
        "category": "其他",
        "difficulty": 2,
        "enabled": true,
        "created_at": "2026-01-14 03:03:24",
        "updated_at": "2026-01-14 03:03:24",
        "_source": "database",
        "_matchScore": 1
      },
      {
        "id": 2228,
        "word": "share",
        "phonetic": "",
        "pos": "v.",
        "meaning": "合用；分享 n.(C)一份；股票",
        "example": "",
        "irregular_forms": {},
        "category": "其他",
        "difficulty": 2,
        "enabled": true,
        "created_at": "2026-01-14 03:03:25",
        "updated_at": "2026-01-14 03:03:25",
        "_source": "database",
        "_matchScore": 1
      },
      {
        "id": 2429,
        "word": "surprise",
        "phonetic": "",
        "pos": "n.",
        "meaning": "(C/U)惊奇 nt.使惊奇，使诧异",
        "example": "",
        "irregular_forms": {},
        "category": "其他",
        "difficulty": 2,
        "enabled": true,
        "created_at": "2026-01-14 03:03:25",
        "updated_at": "2026-01-14 03:03:25",
        "_source": "database",
        "_matchScore": 1
      },
      {
        "id": 2690,
        "word": "website",
        "phonetic": "",
        "pos": "n.(C)",
        "meaning": "网站",
        "example": "",
        "irregular_forms": {},
        "category": "其他",
        "difficulty": 2,
        "enabled": true,
        "created_at": "2026-01-14 03:03:26",
        "updated_at": "2026-01-14 03:03:26",
        "_source": "database",
        "_matchScore": 1
      },
      {
        "id": 1637,
        "word": "minus",
        "phonetic": "",
        "pos": "prep.",
        "meaning": "减",
        "example": "",
        "irregular_forms": {},
        "category": "其他",
        "difficulty": 2,
        "enabled": true,
        "created_at": "2026-01-14 03:03:24",
        "updated_at": "2026-01-14 03:03:24",
        "_source": "database",
        "_matchScore": 1
      },
      {
        "id": 328,
        "word": "bath",
        "phonetic": "",
        "pos": "n.(C)",
        "meaning": "洗澡",
        "example": "",
        "irregular_forms": {},
        "category": "其他",
        "difficulty": 2,
        "enabled": true,
        "created_at": "2026-01-14 03:03:21",
        "updated_at": "2026-01-14 03:03:21",
        "_source": "database",
        "_matchScore": 1
      },
      {
        "id": 329,
        "word": "bathe",
        "phonetic": "",
        "pos": "v.",
        "meaning": "洗澡",
        "example": "",
        "irregular_forms": {},
        "category": "其他",
        "difficulty": 2,
        "enabled": true,
        "created_at": "2026-01-14 03:03:21",
        "updated_at": "2026-01-14 03:03:21",
        "_source": "database",
        "_matchScore": 1
      },
      {
        "id": 426,
        "word": "breathe",
        "phonetic": "",
        "pos": "v.",
        "meaning": "呼吸",
        "example": "",
        "irregular_forms": {},
        "category": "其他",
        "difficulty": 2,
        "enabled": true,
        "created_at": "2026-01-14 03:03:21",
        "updated_at": "2026-01-14 03:03:21",
        "_source": "database",
        "_matchScore": 1
      },
      {
        "id": 1213,
        "word": "grow",
        "phonetic": "",
        "pos": "v.",
        "meaning": "生长；发育；种植",
        "example": "",
        "irregular_forms": {},
        "category": "其他",
        "difficulty": 2,
        "enabled": true,
        "created_at": "2026-01-14 03:03:23",
        "updated_at": "2026-01-14 03:03:23",
        "_source": "database",
        "_matchScore": 1
      },
      {
        "id": 2543,
        "word": "top",
        "phonetic": "",
        "pos": "n.(C)",
        "meaning": "顶部 adj. 居首位的；最上面的",
        "example": "",
        "irregular_forms": {},
        "category": "食物饮品",
        "difficulty": 2,
        "enabled": true,
        "created_at": "2026-01-14 03:03:26",
        "updated_at": "2026-01-14 03:03:26",
        "_source": "database",
        "_matchScore": 1
      },
      {
        "id": 2655,
        "word": "volunteer",
        "phonetic": "",
        "pos": "n.(C)",
        "meaning": "志愿者 v.自愿去做",
        "example": "",
        "irregular_forms": {},
        "category": "其他",
        "difficulty": 2,
        "enabled": true,
        "created_at": "2026-01-14 03:03:26",
        "updated_at": "2026-01-14 03:03:26",
        "_source": "database",
        "_matchScore": 1
      },
      {
        "id": 275,
        "word": "article",
        "phonetic": "",
        "pos": "n.",
        "meaning": "文章",
        "example": "",
        "irregular_forms": {},
        "category": "其他",
        "difficulty": 2,
        "enabled": true,
        "created_at": "2026-01-14 03:03:21",
        "updated_at": "2026-01-14 03:03:21",
        "_source": "database",
        "_matchScore": 1
      },
      {
        "id": 952,
        "word": "exact",
        "phonetic": "",
        "pos": "adj.",
        "meaning": "确切的；准确的",
        "example": "",
        "irregular_forms": {},
        "category": "其他",
        "difficulty": 2,
        "enabled": true,
        "created_at": "2026-01-14 03:03:22",
        "updated_at": "2026-01-14 03:03:22",
        "_source": "database",
        "_matchScore": 1
      },
      {
        "id": 1122,
        "word": "fresh",
        "phonetic": "",
        "pos": "adj.",
        "meaning": "新鲜的",
        "example": "",
        "irregular_forms": {},
        "category": "其他",
        "difficulty": 2,
        "enabled": true,
        "created_at": "2026-01-14 03:03:23",
        "updated_at": "2026-01-14 03:03:23",
        "_source": "database",
        "_matchScore": 1
      },
      {
        "id": 780,
        "word": "difficulty",
        "phonetic": "",
        "pos": "n.",
        "meaning": "(C/U)困难",
        "example": "",
        "irregular_forms": {},
        "category": "其他",
        "difficulty": 2,
        "enabled": true,
        "created_at": "2026-01-14 03:03:22",
        "updated_at": "2026-01-14 03:03:22",
        "_source": "database",
        "_matchScore": 1
      },
      {
        "id": 829,
        "word": "double",
        "phonetic": "",
        "pos": "adj.",
        "meaning": "两倍的；双人的",
        "example": "",
        "irregular_forms": {},
        "category": "其他",
        "difficulty": 2,
        "enabled": true,
        "created_at": "2026-01-14 03:03:22",
        "updated_at": "2026-01-14 03:03:22",
        "_source": "database",
        "_matchScore": 1
      },
      {
        "id": 1973,
        "word": "progress",
        "phonetic": "",
        "pos": "n.(U)",
        "meaning": "进步；进展",
        "example": "",
        "irregular_forms": {},
        "category": "其他",
        "difficulty": 2,
        "enabled": true,
        "created_at": "2026-01-14 03:03:24",
        "updated_at": "2026-01-14 03:03:24",
        "_source": "database",
        "_matchScore": 1
      },
      {
        "word": "miss.",
        "phonetic": "/mɪs/",
        "pos": "n. 称呼",
        "meaning": "小姐（未婚女性的称呼）",
        "example": "Miss Liu is our English teacher.",
        "_source": "ai"
      },
      {
        "word": "mister",
        "phonetic": "/ˈmɪstər/",
        "pos": "n. 称呼",
        "meaning": "先生（男性的尊称，完整形式）",
        "example": "Mister Brown is waiting outside.",
        "_source": "ai"
      },
      {
        "word": "mr.",
        "phonetic": "/ˈmɪstər/",
        "pos": "n. 称呼",
        "meaning": "先生（Mr. 的缩写，男性尊称）",
        "example": "Mr. Smith works in the bank.",
        "_source": "ai"
      },
      {
        "word": "mrs.",
        "phonetic": "/ˈmɪsɪz/",
        "pos": "n. 称呼",
        "meaning": "太太（已婚女性的称呼）",
        "example": "Mrs. Green has two children.",
        "_source": "ai"
      },
      {
        "word": "ms.",
        "phonetic": "/mɪz/",
        "pos": "n. 称呼",
        "meaning": "女士（不确定或不强调婚姻状况）",
        "example": "Ms. Wang will give a speech.",
        "_source": "ai"
      },
      {
        "word": "unknown",
        "phonetic": "/ˌʌnˈnoʊn/",
        "pos": "adj.",
        "meaning": "未知的，不知道的",
        "example": "The cause of the accident is unknown.",
        "_source": "ai"
      },
      {
        "word": "e.g.",
        "phonetic": "/ˌiː ˈdʒiː/",
        "pos": "abbr.",
        "meaning": "例如（for example 的缩写）",
        "example": "I like fruit, e.g., apples and bananas.",
        "_source": "ai"
      },
      {
        "word": "rewrite",
        "phonetic": "/ˌriːˈraɪt/",
        "pos": "v.",
        "meaning": "重写，改写",
        "example": "Please rewrite the sentence correctly.",
        "_source": "ai"
      },
      {
        "word": "summary",
        "phonetic": "/ˈsʌməri/",
        "pos": "n.",
        "meaning": "总结，概要",
        "example": "Write a short summary of the article.",
        "_source": "ai"
      }
    ],
    "phrases": [
      {
        "id": 2601,
        "phrase": "be important to sb./sth.",
        "meaning": "",
        "example": "",
        "category": "其他",
        "difficulty": 2,
        "enabled": true,
        "created_at": "2026-01-16 05:48:25",
        "updated_at": "2026-01-16 05:48:25",
        "_source": "database",
        "_matchScore": 1
      },
      {
        "id": 2613,
        "phrase": "day by day",
        "meaning": "pr.一天天地；逐渐地",
        "example": "The environment is getting worse day by day.",
        "category": "其他",
        "difficulty": 2,
        "enabled": true,
        "created_at": "2026-01-20 04:29:05",
        "updated_at": "2026-01-20 04:29:05",
        "_source": "database",
        "_matchScore": 1
      },
      {
        "id": 966,
        "phrase": "for example",
        "meaning": "例如",
        "example": "",
        "category": "其他",
        "difficulty": 2,
        "enabled": true,
        "created_at": "2026-01-14 03:03:28",
        "updated_at": "2026-01-14 03:03:28",
        "_source": "database",
        "_matchScore": 1
      },
      {
        "id": 1082,
        "phrase": "go out",
        "meaning": "v.外出；熄灭",
        "example": "",
        "category": "动词短语",
        "difficulty": 2,
        "enabled": true,
        "created_at": "2026-01-14 03:03:28",
        "updated_at": "2026-01-14 03:03:28",
        "_source": "database",
        "_matchScore": 1
      },
      {
        "id": 2268,
        "phrase": "talk about",
        "meaning": "谈论",
        "example": "",
        "category": "动词短语",
        "difficulty": 2,
        "enabled": true,
        "created_at": "2026-01-14 03:03:30",
        "updated_at": "2026-01-14 03:03:30",
        "_source": "database",
        "_matchScore": 1
      },
      {
        "id": 2272,
        "phrase": "talk to sb.",
        "meaning": "和某人交谈/聊天",
        "example": "",
        "category": "动词短语",
        "difficulty": 2,
        "enabled": true,
        "created_at": "2026-01-14 03:03:30",
        "updated_at": "2026-01-14 03:03:30",
        "_source": "database",
        "_matchScore": 1
      },
      {
        "id": 2273,
        "phrase": "talk with",
        "meaning": "同……谈话",
        "example": "",
        "category": "动词短语",
        "difficulty": 2,
        "enabled": true,
        "created_at": "2026-01-14 03:03:30",
        "updated_at": "2026-01-14 03:03:30",
        "_source": "database",
        "_matchScore": 1
      },
      {
        "id": 2445,
        "phrase": "turn off",
        "meaning": "v. 关掉",
        "example": "",
        "category": "动词短语",
        "difficulty": 2,
        "enabled": true,
        "created_at": "2026-01-14 03:03:31",
        "updated_at": "2026-01-14 03:03:31",
        "_source": "database",
        "_matchScore": 1
      },
      {
        "id": 251,
        "phrase": "ask sb. for sth.",
        "meaning": "问某人要……；向某人征求……",
        "example": "",
        "category": "动词短语",
        "difficulty": 2,
        "enabled": true,
        "created_at": "2026-01-14 03:03:27",
        "updated_at": "2026-01-14 03:03:27",
        "_source": "database",
        "_matchScore": 0.95
      },
      {
        "id": 2600,
        "phrase": "be controlled by sb./sth.",
        "meaning": "pr.被……控制",
        "example": "The machine is controlled by a computer.",
        "category": "其他",
        "difficulty": 2,
        "enabled": true,
        "created_at": "2026-01-16 02:14:15",
        "updated_at": "2026-01-16 02:14:15",
        "_source": "database",
        "_matchScore": 1
      },
      {
        "id": 1277,
        "phrase": "in front of",
        "meaning": "adv.在(外部的)前面",
        "example": "",
        "category": "食物饮品",
        "difficulty": 2,
        "enabled": true,
        "created_at": "2026-01-14 03:03:28",
        "updated_at": "2026-01-14 03:03:28",
        "_source": "database",
        "_matchScore": 1
      },
      {
        "id": 2598,
        "phrase": "speak up",
        "meaning": "pr.大声说；说清楚",
        "example": "Please speak up so everyone can hear you.",
        "category": "其他",
        "difficulty": 2,
        "enabled": true,
        "created_at": "2026-01-16 02:10:18",
        "updated_at": "2026-01-16 02:10:18",
        "_source": "database",
        "_matchScore": 1
      },
      {
        "id": 1268,
        "phrase": "in class",
        "meaning": "在课堂上；上课中",
        "example": "",
        "category": "时间日期",
        "difficulty": 2,
        "enabled": true,
        "created_at": "2026-01-14 03:03:28",
        "updated_at": "2026-01-14 03:03:28",
        "_source": "database",
        "_matchScore": 1
      },
      {
        "id": 2605,
        "phrase": "on the top of",
        "meaning": "pr.在...顶端",
        "example": "",
        "category": "其他",
        "difficulty": 2,
        "enabled": true,
        "created_at": "2026-01-16 06:24:14",
        "updated_at": "2026-01-16 06:24:14",
        "_source": "database",
        "_matchScore": 1
      },
      {
        "id": 1189,
        "phrase": "have trouble with sth.",
        "meaning": "v.做……很吃力",
        "example": "",
        "category": "食物饮品",
        "difficulty": 2,
        "enabled": true,
        "created_at": "2026-01-14 03:03:28",
        "updated_at": "2026-01-14 03:03:28",
        "_source": "database",
        "_matchScore": 0.85
      },
      {
        "id": 2609,
        "phrase": "make progress",
        "meaning": "pr.取得进步",
        "example": "She has made great progress.",
        "category": "其他",
        "difficulty": 2,
        "enabled": true,
        "created_at": "2026-01-16 06:36:28",
        "updated_at": "2026-01-16 06:36:28",
        "_source": "database",
        "_matchScore": 1
      },
      {
        "phrase": "in the crowd",
        "meaning": "在人群中",
        "example": "I saw him in the crowd.",
        "_source": "ai"
      },
      {
        "phrase": "on a website",
        "meaning": "在网站上",
        "example": "The news is posted on a website.",
        "_source": "ai"
      },
      {
        "phrase": "share ideas",
        "meaning": "分享想法",
        "example": "Students share ideas in class.",
        "_source": "ai"
      },
      {
        "phrase": "in a smart garden",
        "meaning": "在智能花园里",
        "example": "Plants grow well in a smart garden.",
        "_source": "ai"
      },
      {
        "phrase": "write down",
        "meaning": "写下，记下",
        "example": "Please write down the key points.",
        "_source": "ai"
      },
      {
        "phrase": "from the article",
        "meaning": "来自文章",
        "example": "We learned this fact from the article.",
        "_source": "ai"
      },
      {
        "phrase": "with difficulty",
        "meaning": "困难地，费力地",
        "example": "He walked with difficulty.",
        "_source": "ai"
      }
    ],
    "patterns": [
      {
        "pattern": "more and more + adj.",
        "meaning": "越来越……",
        "example": "The weather is getting more and more cold.",
        "_source": "ai"
      },
      {
        "pattern": "tell sb. sth.",
        "meaning": "告诉某人某事",
        "example": "She told me the truth.",
        "_source": "ai"
      },
      {
        "pattern": "ask sb. for sth.",
        "meaning": "向某人要某物",
        "example": "He asked the teacher for help.",
        "_source": "ai"
      },
      {
        "pattern": "sb. can be + adj.",
        "meaning": "某人可能是……",
        "example": "The task can be difficult.",
        "_source": "ai"
      },
      {
        "pattern": "without + doing",
        "meaning": "没有做某事",
        "example": "He left without saying goodbye.",
        "_source": "ai"
      },
      {
        "pattern": "what does sb. teach sb.?",
        "meaning": "某人教某人什么？",
        "example": "What does she teach the students?",
        "_source": "ai"
      }
    ]
  },
  "grammar": [
    {
      "id": 10,
      "title": "动名词 (v.-ing作名词)",
      "keywords": [
        "动名词",
        "doing",
        "v.-ing",
        "gerund",
        "动词-ing形式"
      ],
      "definition": "由动词-ing形式构成，具有名词性质，可以作主语、宾语、表语等。",
      "structure": "动词-ing",
      "usage": [
        "作主语：Swimming is good for health.",
        "作宾语：I enjoy reading books. / Thank you for helping me.",
        "作表语：My hobby is collecting stamps.",
        "某些动词后只能接动名词：enjoy, finish, mind, practice, avoid, consider等"
      ],
      "mistakes": [
        {
          "wrong": "I enjoy to swim.",
          "correct": "I enjoy swimming.",
          "explanation": "enjoy后只能接动名词，不能接不定式"
        },
        {
          "wrong": "Thank you for help me.",
          "correct": "Thank you for helping me.",
          "explanation": "介词后要用动名词"
        }
      ],
      "examples": [
        "Reading makes a full man.",
        "Would you mind opening the window?",
        "She is good at playing the piano."
      ],
      "sub_topics": [],
      "category": "其他",
      "difficulty": 2,
      "enabled": true,
      "is_new": false,
      "created_at": "2026-01-14 02:03:24",
      "updated_at": "2026-01-14 02:03:24",
      "_source": "database",
      "_matchScore": 1
    },
    {
      "id": 41,
      "title": "否定句",
      "keywords": [
        "否定句"
      ],
      "definition": "表示否定意义的句子",
      "structure": "be not / do not",
      "usage": [
        "注意助动词"
      ],
      "mistakes": [],
      "examples": [
        "He does not like milk."
      ],
      "sub_topics": [],
      "category": "其他",
      "difficulty": 2,
      "enabled": true,
      "is_new": false,
      "created_at": "2026-01-16 13:50:18",
      "updated_at": "2026-01-16 13:50:18",
      "_source": "database",
      "_matchScore": 1
    },
    {
      "id": 8,
      "title": "被动语态",
      "keywords": [
        "被动语态",
        "be done",
        "被动",
        "by",
        "passive voice",
        "被动形式"
      ],
      "definition": "当主语是动作的承受者时，使用被动语态。强调动作的承受者或动作本身。",
      "structure": "主语 + be + 过去分词 + (by + 动作执行者)",
      "usage": [
        "不知道或不必说明动作执行者：The window was broken.",
        "强调动作承受者：The book was written by Lu Xun.",
        "客观报道或正式场合：The meeting will be held tomorrow.",
        "各种时态的被动：is done, was done, will be done, has been done等"
      ],
      "mistakes": [
        {
          "wrong": "The car was repair yesterday.",
          "correct": "The car was repaired yesterday.",
          "explanation": "be后面要用动词的过去分词"
        },
        {
          "wrong": "The book is belonged to me.",
          "correct": "The book belongs to me.",
          "explanation": "belong是不及物动词，没有被动语态"
        }
      ],
      "examples": [
        "English is spoken all over the world.",
        "The bridge was built in 1990.",
        "The work must be finished on time."
      ],
      "sub_topics": [],
      "category": "语态",
      "difficulty": 2,
      "enabled": true,
      "is_new": false,
      "created_at": "2026-01-14 02:03:24",
      "updated_at": "2026-01-14 02:03:24",
      "_source": "database",
      "_matchScore": 1
    },
    {
      "title": "现在进行时表示变化趋势",
      "definition": "用现在进行时表示事物正在发生变化的趋势。",
      "structure": "be + getting + 比较级",
      "usage": [
        "描述逐渐变化的情况",
        "常与时间状语连用"
      ],
      "examples": [
        "The weather is getting warmer.",
        "Life is getting better."
      ],
      "_source": "ai"
    },
    {
      "title": "主谓一致",
      "definition": "主语和谓语在人称和数上保持一致。",
      "structure": "第三人称单数/不可数名词 + 动词三单",
      "usage": [
        "he/she/it 作主语",
        "不可数名词作主语"
      ],
      "examples": [
        "He likes English.",
        "Water is important."
      ],
      "_source": "ai"
    },
    {
      "title": "递增比较级结构",
      "definition": "表示程度不断加深。",
      "structure": "more and more + 形容词",
      "usage": [
        "描述持续变化",
        "常用于写作"
      ],
      "examples": [
        "The city is becoming more and more beautiful."
      ],
      "_source": "ai"
    },
    {
      "title": "逗号不能连接两个完整句",
      "definition": "英语中不能用逗号直接连接两个完整句子。",
      "structure": "句子 + 连词 + 句子",
      "usage": [
        "用 and/but/so 等连词",
        "或分号/句号"
      ],
      "examples": [
        "I like English, and I study it every day."
      ],
      "_source": "ai"
    },
    {
      "title": "英语句子必须有主语",
      "definition": "英语句子中必须出现主语。",
      "structure": "形式主语 it + be + adj. + to do",
      "usage": [
        "避免无主句",
        "常用 it 作形式主语"
      ],
      "examples": [
        "It is important to study hard."
      ],
      "_source": "ai"
    },
    {
      "title": "代词指代一致",
      "definition": "代词的单复数和所指对象保持一致。",
      "structure": "it / them / this",
      "usage": [
        "避免指代不明",
        "保持前后一致"
      ],
      "examples": [
        "I bought apples. They are fresh."
      ],
      "_source": "ai"
    },
    {
      "title": "介词 to 表示“对某人”",
      "definition": "to 表示动作或状态的对象。",
      "structure": "be + adj. + to sb.",
      "usage": [
        "常见于形容词后",
        "表示影响对象"
      ],
      "examples": [
        "The book is important to me."
      ],
      "_source": "ai"
    },
    {
      "title": "不规则动词变化",
      "definition": "不规则动词的过去式和过去分词形式不遵循规则。",
      "structure": "原形-过去式-过去分词",
      "usage": [
        "需单独记忆",
        "常考点"
      ],
      "examples": [
        "tell-told-told",
        "speak-spoke-spoken",
        "say-said-said"
      ],
      "_source": "ai"
    },
    {
      "title": "过去式的用法",
      "definition": "表示过去发生的动作或状态。",
      "structure": "动词过去式",
      "usage": [
        "与过去时间状语连用"
      ],
      "examples": [
        "I ate breakfast at 7."
      ],
      "_source": "ai"
    },
    {
      "title": "过去分词的三种用法",
      "definition": "过去分词可用于完成时、被动语态和作形容词。",
      "structure": "have/has + 过去分词；be + 过去分词",
      "usage": [
        "现在完成时",
        "被动语态",
        "作定语"
      ],
      "examples": [
        "I have finished my homework.",
        "The door is closed.",
        "an eaten apple"
      ],
      "_source": "ai"
    },
    {
      "title": "现在完成时",
      "definition": "表示过去发生并与现在有关的动作。",
      "structure": "have/has + 过去分词",
      "usage": [
        "强调结果或经验"
      ],
      "examples": [
        "She has visited Beijing."
      ],
      "_source": "ai"
    },
    {
      "title": "动名词作主语",
      "definition": "动名词短语作主语视为单数。",
      "structure": "doing sth. + 谓语单数",
      "usage": [
        "描述行为本身"
      ],
      "examples": [
        "Reading books makes me happy."
      ],
      "_source": "ai"
    },
    {
      "title": "see 的宾补结构",
      "definition": "see 后可接宾语 + do/doing。",
      "structure": "see sb. do/doing sth.",
      "usage": [
        "do 表示全过程",
        "doing 表示正在进行"
      ],
      "examples": [
        "I saw him cross the road.",
        "I saw him crossing the road."
      ],
      "_source": "ai"
    },
    {
      "title": "invite 的固定用法",
      "definition": "invite 只能接不定式作宾补。",
      "structure": "invite sb. to do sth.",
      "usage": [
        "表示邀请未发生的动作"
      ],
      "examples": [
        "She invited me to join the party."
      ],
      "_source": "ai"
    },
    {
      "title": "一般疑问句",
      "definition": "把助动词/系动词提前构成疑问句。",
      "structure": "Do/Does/Did + 主语 + 动词原形",
      "usage": [
        "根据谓语判断助动词"
      ],
      "examples": [
        "Do you like English?"
      ],
      "_source": "ai"
    },
    {
      "title": "特殊疑问句",
      "definition": "用疑问词对句子成分提问。",
      "structure": "Wh- + 一般疑问句语序",
      "usage": [
        "先确定提问成分"
      ],
      "examples": [
        "What does he teach students?"
      ],
      "_source": "ai"
    },
    {
      "title": "定语从句（后置定语）",
      "definition": "用从句修饰名词，放在名词后。",
      "structure": "名词 + that/which + 从句",
      "usage": [
        "修饰人或物",
        "阅读常见"
      ],
      "examples": [
        "The boy who is reading is my brother."
      ],
      "_source": "ai"
    },
    {
      "title": "动词双宾语",
      "definition": "部分动词可接两个宾语。",
      "structure": "teach sb. sth. / teach sth. to sb.",
      "usage": [
        "人作间接宾语"
      ],
      "examples": [
        "She teaches us English."
      ],
      "_source": "ai"
    },
    {
      "title": "spend 的用法",
      "definition": "spend 表示花费时间或金钱。",
      "structure": "spend + 时间/金钱 + doing sth.",
      "usage": [
        "主语通常是人"
      ],
      "examples": [
        "He spent the whole summer studying."
      ],
      "_source": "ai"
    },
    {
      "title": "合并句子",
      "definition": "主语相同的句子可省略重复主语。",
      "structure": "主语 + 动词 … and + 动词 …",
      "usage": [
        "避免重复",
        "提高表达"
      ],
      "examples": [
        "He opened the door and walked in."
      ],
      "_source": "ai"
    }
  ],
  "summary": {
    "total_words": 51,
    "total_phrases": 23,
    "total_patterns": 6,
    "total_grammar": 23
  },
  "metadata": {
    "taskId": "0ff42e69-e2b6-4582-b81e-3da97f487dee",
    "originalFile": "1月7日课堂笔记.txt",
    "processedAt": "2026-01-20T08:03:47.900Z",
    "totalSegments": 7,
    "successCount": 7,
    "failCount": 0,
    "browserRestarts": 1
  }
}