{
  "vocabulary": {
    "words": [],
    "phrases": [
      {
        "id": 2621,
        "phrase": "there be",
        "meaning": "pr. 有",
        "example": "",
        "category": "其他",
        "difficulty": 2,
        "enabled": true,
        "created_at": "2026-01-21 10:27:24",
        "updated_at": "2026-01-21 02:27:24",
        "is_new": false,
        "_source": "database",
        "_matchScore": 1
      },
      {
        "id": 2638,
        "phrase": "so ... that ...",
        "meaning": "pr. 如此. .. 以至于. ..",
        "example": "",
        "category": "其他",
        "difficulty": 2,
        "enabled": true,
        "created_at": "2026-02-01 21:28:18",
        "updated_at": "2026-02-01 13:28:18",
        "is_new": true,
        "_source": "database",
        "_matchScore": 1
      },
      {
        "id": 2639,
        "phrase": "too ... to ...",
        "meaning": "pr. 太. .. 而不能. ..",
        "example": "",
        "category": "其他",
        "difficulty": 2,
        "enabled": true,
        "created_at": "2026-02-01 21:28:51",
        "updated_at": "2026-02-01 13:28:51",
        "is_new": true,
        "_source": "database",
        "_matchScore": 1
      },
      {
        "id": 2152,
        "phrase": "spend time/money in doing sth.",
        "meaning": "v. 花费时间/金钱做某事",
        "example": "",
        "category": "时间日期",
        "difficulty": 2,
        "enabled": true,
        "created_at": "2026-01-14 03:03:30",
        "updated_at": "2026-01-14 03:03:30",
        "is_new": false,
        "_source": "database",
        "_matchScore": 1
      }
    ],
    "patterns": [
      {
        "id": 108,
        "pattern": "not only...but also...",
        "meaning": "不仅……而且……",
        "example": "",
        "category": "其他",
        "difficulty": 2,
        "enabled": true,
        "created_at": "2026-01-14 03:03:31",
        "updated_at": "2026-01-14 03:03:31",
        "is_new": false,
        "_source": "database",
        "_matchScore": 1
      },
      {
        "id": 79,
        "pattern": "either...or...",
        "meaning": "要么……要么, ……或……",
        "example": "",
        "category": "其他",
        "difficulty": 2,
        "enabled": true,
        "created_at": "2026-01-14 03:03:31",
        "updated_at": "2026-01-14 03:03:31",
        "is_new": false,
        "_source": "database",
        "_matchScore": 1
      },
      {
        "id": 89,
        "pattern": "how about doing sth.?",
        "meaning": "做某事怎么样?",
        "example": "",
        "category": "其他",
        "difficulty": 2,
        "enabled": true,
        "created_at": "2026-01-14 03:03:31",
        "updated_at": "2026-01-14 03:03:31",
        "is_new": false,
        "_source": "database",
        "_matchScore": 1
      }
    ]
  },
  "grammar": [
    {
      "id": 18,
      "title": "感叹句",
      "keywords": [
        "感叹句",
        "what",
        "how",
        "感叹",
        "exclamatory sentence"
      ],
      "definition": "用来表达强烈感情的句子，句末用感叹号。常用What和How引导。",
      "structure": "What + (a/an) + 形容词 + 名词 + 主语 + 谓语! / How + 形容词/副词 + 主语 + 谓语!",
      "usage": [
        "What + a/an + 形容词 + 可数名词单数：What a beautiful girl she is!",
        "What + 形容词 + 不可数名词/复数名词：What nice weather! What beautiful flowers!",
        "How + 形容词/副词：How beautiful the girl is! How fast he runs!",
        "判断用What还是How：看中心词是名词还是形容词/副词"
      ],
      "mistakes": [
        {
          "wrong": "What beautiful girl she is!",
          "correct": "What a beautiful girl she is!",
          "explanation": "可数名词单数前要加a/an"
        },
        {
          "wrong": "How a beautiful girl!",
          "correct": "What a beautiful girl! / How beautiful the girl is!",
          "explanation": "How后直接加形容词，不加冠词和名词"
        },
        {
          "wrong": "What nice the weather is!",
          "correct": "How nice the weather is! / What nice weather!",
          "explanation": "What后要有名词，How后直接加形容词"
        }
      ],
      "examples": [
        "What an interesting story it is!",
        "What delicious food!",
        "How time flies!"
      ],
      "sub_topics": [
        {
          "title": "how adj. .!",
          "source_type": "unmatched",
          "source_id": 1958,
          "definition": "",
          "structure": "",
          "usage": [],
          "examples": [],
          "mistakes": [],
          "added_at": "2026-02-02T06:55:37.871Z",
          "order": 0
        }
      ],
      "category": "句式",
      "difficulty": 2,
      "enabled": true,
      "is_new": false,
      "created_at": "2026-01-14 02:03:25",
      "updated_at": "2026-02-02 06:55:37",
      "_source": "database",
      "_matchScore": 1
    },
    {
      "id": 91,
      "title": "make",
      "keywords": [
        "make"
      ],
      "definition": "使役动词",
      "structure": "make的使役用法",
      "usage": [],
      "mistakes": [],
      "examples": [],
      "sub_topics": [
        {
          "title": "make的使役用法",
          "source_type": "unmatched",
          "source_id": 1576,
          "definition": "",
          "structure": "",
          "usage": [],
          "examples": [],
          "mistakes": []
        }
      ],
      "category": "其他",
      "difficulty": 2,
      "enabled": true,
      "is_new": false,
      "created_at": "2026-01-22 03:18:18",
      "updated_at": "2026-01-23 05:49:08",
      "_source": "database",
      "_matchScore": 1
    },
    {
      "id": 19,
      "title": "祈使句",
      "keywords": [
        "祈使句",
        "动词原形开头",
        "don't",
        "let",
        "please",
        "imperative sentence"
      ],
      "definition": "用来表示请求、命令、建议、劝告等的句子，通常省略主语you。",
      "structure": "动词原形 + 其他 / Don't + 动词原形 + 其他 / Let + 宾语 + 动词原形",
      "usage": [
        "肯定祈使句：Open the door, please.",
        "否定祈使句：Don't be late. / Never give up.",
        "Let句型：Let me help you. / Let's go.",
        "反义疑问句：Open the door, will you? / Let's go, shall we?"
      ],
      "mistakes": [
        {
          "wrong": "Don't to be noisy.",
          "correct": "Don't be noisy.",
          "explanation": "Don't后直接加动词原形，不需要to"
        },
        {
          "wrong": "Please you come here.",
          "correct": "Please come here.",
          "explanation": "祈使句通常省略主语you"
        },
        {
          "wrong": "Let's go, will we?",
          "correct": "Let's go, shall we?",
          "explanation": "Let's的反义疑问句用shall we"
        }
      ],
      "examples": [
        "Be quiet, please.",
        "Don't touch it!",
        "Let him do it himself."
      ],
      "sub_topics": [],
      "category": "句式",
      "difficulty": 2,
      "enabled": true,
      "is_new": false,
      "created_at": "2026-01-14 02:03:25",
      "updated_at": "2026-01-14 02:03:25",
      "_source": "database",
      "_matchScore": 1
    },
    {
      "id": 25,
      "title": "冠词",
      "keywords": [
        "冠词",
        "a",
        "an",
        "the",
        "不定冠词",
        "定冠词",
        "零冠词",
        "article"
      ],
      "definition": "用在名词前，说明名词所指的人或事物。分为不定冠词(a/an)、定冠词(the)和零冠词。",
      "structure": "冠词 + (形容词) + 名词",
      "usage": [
        "a/an用于泛指单数可数名词：a book, an apple (元音音素前用an)",
        "the用于特指、上文提过、独一无二的事物：the sun, the book I bought",
        "the + 形容词表示一类人：the rich (富人), the young (年轻人)",
        "零冠词：复数名词和不可数名词泛指、球类运动、三餐、学科等"
      ],
      "mistakes": [
        {
          "wrong": "I have a umbrella.",
          "correct": "I have an umbrella.",
          "explanation": "umbrella以元音音素开头，用an"
        },
        {
          "wrong": "He is an university student.",
          "correct": "He is a university student.",
          "explanation": "university虽以u开头，但发音是辅音/ju:/，用a"
        },
        {
          "wrong": "I like playing the football.",
          "correct": "I like playing football.",
          "explanation": "球类运动前不加冠词"
        }
      ],
      "examples": [
        "I saw a dog. The dog was very cute.",
        "The moon goes around the earth.",
        "We should help the poor."
      ],
      "sub_topics": [],
      "category": "其他",
      "difficulty": 2,
      "enabled": true,
      "is_new": false,
      "created_at": "2026-01-14 02:03:25",
      "updated_at": "2026-01-14 02:03:25",
      "_source": "database",
      "_matchScore": 1
    },
    {
      "id": 28,
      "title": "常用介词",
      "keywords": [
        "介词",
        "in",
        "on",
        "at",
        "for",
        "by",
        "with",
        "preposition",
        "介词搭配"
      ],
      "definition": "用在名词、代词或动名词前，表示时间、地点、方式、原因等关系的词。",
      "structure": "介词 + 名词/代词/动名词",
      "usage": [
        "时间：at+时刻, on+具体日期, in+年月季节长时段",
        "地点：at+小地点, in+大地点/里面, on+表面",
        "方式：by+交通工具/方式, with+工具/材料, in+语言/颜色",
        "常见搭配：be good at, be interested in, look for, wait for, listen to"
      ],
      "mistakes": [
        {
          "wrong": "I arrived at Beijing.",
          "correct": "I arrived in Beijing.",
          "explanation": "arrive in+大地点，arrive at+小地点"
        },
        {
          "wrong": "I go to school by a bus.",
          "correct": "I go to school by bus.",
          "explanation": "by+交通工具中间不加冠词"
        },
        {
          "wrong": "I'm looking forward to see you.",
          "correct": "I'm looking forward to seeing you.",
          "explanation": "look forward to后面接动名词"
        }
      ],
      "examples": [
        "The meeting will be held at 3 o'clock on Monday.",
        "She goes to work by subway.",
        "He is good at playing basketball."
      ],
      "sub_topics": [
        {
          "title": "介词to和for的用法区别",
          "source_type": "unmatched",
          "source_id": 1002,
          "definition": "to强调动作结果指向，for强调受益对象",
          "structure": "be important to sb.; be good for sb.",
          "usage": [
            "to表示方向或结果",
            "for表示受益或用途"
          ],
          "examples": [
            "This book is important to me.",
            "Exercise is good for your health."
          ],
          "mistakes": [],
          "added_at": "2026-01-21T01:07:32.540Z",
          "order": 0
        },
        {
          "title": "介词后只能接名词",
          "source_type": "unmatched",
          "source_id": 1011,
          "definition": "介词后不能直接接动词原形",
          "structure": "介词 + 名词/doing",
          "usage": [
            "to do中的to不是介词"
          ],
          "examples": [
            "without water",
            "without eating"
          ],
          "mistakes": [],
          "added_at": "2026-01-21T01:10:24.387Z",
          "order": 1
        },
        {
          "title": "介词without的用法（后接名词或动名词）",
          "source_type": "unmatched",
          "source_id": 1027,
          "definition": "pr.邀请某人做某事",
          "structure": "",
          "usage": [],
          "examples": [],
          "mistakes": [],
          "added_at": "2026-01-21T01:23:52.747Z",
          "order": 2
        },
        {
          "title": "介词without的用法",
          "source_type": "unmatched",
          "source_id": 1124,
          "definition": "without表示“没有”，后接名词或doing。",
          "structure": "without + 名词/doing",
          "usage": [
            "表示缺少某物或行为"
          ],
          "examples": [
            "He left without saying goodbye.",
            "She passed the exam without effort."
          ],
          "mistakes": [],
          "added_at": "2026-01-21T02:10:31.977Z",
          "order": 3
        },
        {
          "title": "介词to的用法",
          "source_type": "unmatched",
          "source_id": 1519,
          "definition": "pr.从后到前",
          "structure": "",
          "usage": [],
          "examples": [],
          "mistakes": [],
          "added_at": "2026-01-22T00:58:03.936Z",
          "order": 4
        }
      ],
      "category": "其他",
      "difficulty": 2,
      "enabled": true,
      "is_new": false,
      "created_at": "2026-01-14 02:03:25",
      "updated_at": "2026-01-22 00:58:03",
      "_source": "database",
      "_matchScore": 1
    },
    {
      "title": "see sb. do sth.",
      "definition": "v.看见某人做某事(经常发生)",
      "_source": "database"
    }
  ],
  "summary": {
    "total_words": 0,
    "total_phrases": 4,
    "total_patterns": 3,
    "total_grammar": 6
  },
  "metadata": {
    "taskId": "6588f920-ca6a-48ec-b9ae-090ec1cdb664",
    "originalFile": "test_cases_40.txt",
    "processedAt": "2026-02-02T06:57:42.644Z",
    "totalSegments": 1,
    "successCount": 1,
    "failCount": 0,
    "browserRestarts": 1
  }
}